[{"content_title":"楚雄大姚彝族群众喜迎插花节","created_at":"2022年03月11日 10:29","url":"http://www.yntv.cn/video/20220311/1646994258192305.html"},{"content_title":"冬残奥赛场云南选手再创佳绩 永不言弃诠释奥林匹克精神","created_at":"2022年03月11日 10:29","url":"http://www.yntv.cn/video/20220311/1646994287192307.html"},{"content_title":"国家发展改革委与在滇全国人大代表进行视频会谈","created_at":"2022年03月11日 10:29","url":"http://www.yntv.cn/video/20220311/1646994302192309.html"},{"content_title":"林文勋：立足自身优势 实现更高质量的内涵式发展","created_at":"2022年03月11日 10:29","url":"http://www.yntv.cn/video/20220311/1646994314192311.html"},{"content_title":"云南省代表团分组审议各项决议草案","created_at":"2022年03月11日 10:29","url":"http://www.yntv.cn/video/20220311/1646994316192313.html"},{"content_title":"石林西街口人参果成功注册国家地理标志证明商标","created_at":"2022年03月11日 10:29","url":"http://www.yntv.cn/video/20220311/1646994320192315.html"},{"content_title":"云南市场主体总数超过415万户 净增数量创历史新高","created_at":"2022年03月11日 10:29","url":"http://www.yntv.cn/video/20220311/1646994322192317.html"},{"content_title":"深入打好污染防治攻坚战 省生态环境厅举行2022年系列新闻发布会第一场发布","created_at":"2022年03月11日 10:29","url":"http://www.yntv.cn/video/20220311/1646994332192319.html"},{"content_title":"站位全局 立足云南 心系人民 云南代表团共向大会提交议案建议250件","created_at":"2022年03月11日 10:29","url":"http://www.yntv.cn/video/20220311/1646994346192321.html"},{"content_title":"王宁王予波看望采访报道全国两会的新闻工作者","created_at":"2022年03月11日 10:29","url":"http://www.yntv.cn/video/20220311/1646994358192323.html"},{"content_title":"旅游收入实现万亿级跨越 云南聚力打造旅游支柱产业","created_at":"2022年03月11日 10:29","url":"http://www.yntv.cn/video/20220311/1646994365192325.html"},{"content_title":"做服务企业的店小二 为高质量发展保驾护航","created_at":"2022年03月11日 10:29","url":"http://www.yntv.cn/video/20220311/1646994369192327.html"},{"content_title":"凝心聚力向未来 昂首奋进新征程 全国政协十三届五次会议在京闭幕","created_at":"2022年03月11日 10:29","url":"http://www.yntv.cn/video/20220311/1646994373192329.html"}]